<?xml version="1.0" encoding="iso-8859-1" standalone="yes" ?>

<izpack:langpack version="5.0"
                 xmlns:izpack="http://izpack.org/schema/langpack"
                 xmlns:xsi="http://www.w3.org/2001/XMLSchema-instance"
                 xsi:schemaLocation="http://izpack.org/schema/langpack http://izpack.org/schema/5.0/izpack-langpack-5.0.xsd">
                 
    <str id="installer.madewith" txt="http://www.logicaldoc.com"/>
    <str id="installer.reversetitle" txt="$APP_NAME $APP_VER"/>
    <str id="installer.title" txt="$APP_NAME $APP_VER"/>
    <str id="installer.close" txt="Fermer"/>
    <str id="data.validation.warning.title" txt="Attention"/>
    
    <str id="embeddeddbwarn" txt="Vous avez choisi d'installer avec le db embedded.\nVos données ne seront pas disponibles dans le système de production.\nConfirmez-vous?" />
    
    <str id="invalidcredentials" txt="Pouvoirs ou fonctionnalité non valide pas activé dans la licence"/>
    
    <str id="invalidjava" txt="Impossible de trouver un Java 8 ou plus pour l'architecture choisie"/>
    
    <str id="TargetPanel.existingLogicalDOC"
         txt="Installation existante détectée! S'il vous plaît appliquer le package de mise à jour appropriée si vous souhaitez mettre à jour votre système."/>
</izpack:langpack>